nayvy/__init__.py
nayvy/console/__init__.py
nayvy/console/cli.py
nayvy/function/__init__.py
nayvy/function/arg.py
nayvy/importing/__init__.py
nayvy/importing/fixer.py
nayvy/importing/flake8.py
nayvy/importing/import_config.py
nayvy/importing/import_statement.py
nayvy/importing/pyflakes.py
nayvy/importing/utils.py
nayvy/projects/__init__.py
nayvy/projects/modules/__init__.py
nayvy/projects/modules/loader.py
nayvy/projects/modules/models.py
nayvy/projects/path.py
nayvy/testing/__init__.py
nayvy/testing/autogen.py
nayvy/testing/path.py
nayvy/utils/colors.py
nayvy-0.1.0.dist-info/entry_points.txt
nayvy-0.1.0.dist-info/WHEEL
nayvy-0.1.0.dist-info/METADATA
nayvy-0.1.0.dist-info/RECORD
